gpt3/__init__.py
gpt3/gpt3.py
gpt3/train.py
gpt3_torch-0.0.9.dist-info/LICENSE
gpt3_torch-0.0.9.dist-info/WHEEL
gpt3_torch-0.0.9.dist-info/METADATA
gpt3_torch-0.0.9.dist-info/RECORD
